Metadata-Version: 2.4
Name: python-documentcloud
Version: 4.5.0
Summary: A simple Python wrapper for the DocumentCloud API
Home-page: https://github.com/muckrock/python-documentcloud
Author: Mitchell Kotler
Author-email: mitch@muckrock.com
License: MIT
Classifier: Development Status :: 5 - Production/Stable
Classifier: Intended Audience :: Developers
Classifier: Operating System :: OS Independent
Classifier: License :: OSI Approved :: MIT License
Classifier: Programming Language :: Python :: 3.8
Classifier: Programming Language :: Python :: 3.9
Classifier: Programming Language :: Python :: 3.10
Classifier: Programming Language :: Python :: 3.11
Classifier: Programming Language :: Python :: 3.12
Classifier: Topic :: Internet :: WWW/HTTP
License-File: LICENSE
Requires-Dist: future
Requires-Dist: listcrunch>=1.0.1
Requires-Dist: python-dateutil
Requires-Dist: ratelimit
Requires-Dist: requests
Requires-Dist: urllib3
Requires-Dist: pyyaml
Requires-Dist: fastjsonschema
Requires-Dist: python-squarelet
Provides-Extra: dev
Requires-Dist: black; extra == "dev"
Requires-Dist: coverage; extra == "dev"
Requires-Dist: isort; extra == "dev"
Requires-Dist: pylint; extra == "dev"
Requires-Dist: sphinx; extra == "dev"
Requires-Dist: twine; extra == "dev"
Provides-Extra: test
Requires-Dist: pytest; extra == "test"
Requires-Dist: pytest-mock; extra == "test"
Requires-Dist: pytest-recording; extra == "test"
Requires-Dist: vcrpy; extra == "test"
Dynamic: author
Dynamic: author-email
Dynamic: classifier
Dynamic: description
Dynamic: description-content-type
Dynamic: home-page
Dynamic: license
Dynamic: license-file
Dynamic: provides-extra
Dynamic: requires-dist
Dynamic: summary
